dbt_quicksight_lineage/__about__.py
dbt_quicksight_lineage/__init__.py
dbt_quicksight_lineage/__main__.py
dbt_quicksight_lineage/cli/__init__.py
dbt_quicksight_lineage/cli/main.py
dbt_quicksight_lineage/cli/requires.py
dbt_quicksight_lineage/core/__init__.py
dbt_quicksight_lineage/core/app.py
dbt_quicksight_lineage/core/dbt.py
dbt_quicksight_lineage/core/quicksight.py
dbt_quicksight_lineage-0.3.2.dist-info/METADATA
dbt_quicksight_lineage-0.3.2.dist-info/WHEEL
dbt_quicksight_lineage-0.3.2.dist-info/entry_points.txt
dbt_quicksight_lineage-0.3.2.dist-info/licenses/LICENSE
dbt_quicksight_lineage-0.3.2.dist-info/RECORD
