Metadata-Version: 2.1
Name: dbt-quicksight-lineage
Version: 0.3.2
Project-URL: Documentation, https://github.com/mashiike/dbt-quicksight-lineage#readme
Project-URL: Issues, https://github.com/mashiike/dbt-quicksight-lineage/issues
Project-URL: Source, https://github.com/mashiike/dbt-quicksight-lineage
Author-email: mashiike <ikeda-masashi@kayac.com>
License-Expression: MIT
License-File: LICENSE
Classifier: Development Status :: 4 - Beta
Classifier: Programming Language :: Python
Classifier: Programming Language :: Python :: 3.10
Classifier: Programming Language :: Python :: 3.11
Classifier: Programming Language :: Python :: Implementation :: CPython
Classifier: Programming Language :: Python :: Implementation :: PyPy
Requires-Python: >=3.10
Requires-Dist: boto3~=1.26.164
Requires-Dist: click~=8.1.3
Requires-Dist: colorlog~=6.7.0
Requires-Dist: dbt-core>=1.5.0
Requires-Dist: ruamel-yaml~=0.17.32
